pyinmean.cpython-38-x86_64-linux-gnu.so
pyinmean-0.1.1.dist-info/LICENSE
pyinmean-0.1.1.dist-info/METADATA
pyinmean-0.1.1.dist-info/WHEEL
pyinmean-0.1.1.dist-info/top_level.txt
pyinmean-0.1.1.dist-info/RECORD
