Metadata-Version: 2.1
Name: pyinmean
Version: 0.1.1
Summary: Python bindings for IMA rhythm analysis
Author: Efraim Dahl, Peter van Kranenburg
Author-email: Efraim Dahl <efraimcdahl@gmail.com>
Maintainer-email: Efraim Dahl <efraimcdahl@gmail.com>
License: GNU General Public License v3.0
Project-URL: Homepage, https://github.com/efraimdahl/pyinmean
Project-URL: Repository, https://github.com/efraimdahl/pyinmean
Project-URL: Issues, https://github.com/efraimdahl/pyinmean/issues
Keywords: IMA,rhythm,music,symbolic music,inner metric weight,spectral weight
Requires-Python: >=3.8
License-File: LICENSE
